metanetx_assets/__init__.py
metanetx_assets/_version.py
metanetx_assets/helpers.py
metanetx_assets/api/__init__.py
metanetx_assets/api/compartment.py
metanetx_assets/api/compound.py
metanetx_assets/api/namespace.py
metanetx_assets/api/reaction.py
metanetx_assets/cli/__init__.py
metanetx_assets/cli/cli.py
metanetx_assets/cli/compartment.py
metanetx_assets/cli/compound.py
metanetx_assets/cli/namespace.py
metanetx_assets/cli/reaction.py
metanetx_assets/etl/__init__.py
metanetx_assets/etl/helpers.py
metanetx_assets/etl/namespace.py
metanetx_assets/etl/reaction.py
metanetx_assets/model/__init__.py
metanetx_assets/model/identifiers_org_namespace_model.py
metanetx_assets/model/identifiers_org_registry_model.py
metanetx_assets-4.2.0.dist-info/LICENSE
metanetx_assets-4.2.0.dist-info/METADATA
metanetx_assets-4.2.0.dist-info/WHEEL
metanetx_assets-4.2.0.dist-info/entry_points.txt
metanetx_assets-4.2.0.dist-info/top_level.txt
metanetx_assets-4.2.0.dist-info/zip-safe
metanetx_assets-4.2.0.dist-info/RECORD
