Metadata-Version: 2.1
Name: metanetx-assets
Version: 4.2.0
Summary: Transform MetaNetX components information and load them into SQL storage.
Home-page: https://github.com/Midnighter/metanetx-assets
Author: Moritz E. Beber
Author-email: midnighter@posteo.net
License: Apache-2.0
Download-URL: https://pypi.org/project/metanetx-assets/
Project-URL: Source Code, https://github.com/Midnighter/metanetx-assets
Project-URL: Bug Tracker, https://github.com/Midnighter/metanetx-assets/issues
Keywords: MetaNetX,SQL,COBRA
Platform: UNKNOWN
Classifier: Development Status :: 2 - Pre-Alpha
Classifier: Intended Audience :: Science/Research
Classifier: License :: OSI Approved :: Apache Software License
Classifier: Natural Language :: English
Classifier: Operating System :: OS Independent
Classifier: Programming Language :: Python :: 3 :: Only
Classifier: Programming Language :: Python :: 3.8
Classifier: Programming Language :: Python :: 3.9
Classifier: Topic :: Scientific/Engineering :: Bio-Informatics
Requires-Python: >=3.7
License-File: LICENSE
Requires-Dist: click (~=7.0)
Requires-Dist: click-log (~=0.3)
Requires-Dist: cobra-component-models
Requires-Dist: depinfo (~=1.5)
Requires-Dist: httpx (~=0.16)
Requires-Dist: pandas (~=1.0)
Requires-Dist: pydantic (~=1.6)
Requires-Dist: pyparsing (~=2.4)
Requires-Dist: SQLAlchemy (~=1.3)
Requires-Dist: tqdm (~=4.0)
Provides-Extra: development
Requires-Dist: black ; extra == 'development'
Requires-Dist: isort ; extra == 'development'
Requires-Dist: pep517 ; extra == 'development'
Requires-Dist: tox ; extra == 'development'
